super_ryaoi_filler/__init__.py
super_ryaoi_filler/super_ryaoi_filler.py
super_ryaoi_filler-0.4.4.dist-info/entry_points.txt
super_ryaoi_filler-0.4.4.dist-info/WHEEL
super_ryaoi_filler-0.4.4.dist-info/METADATA
super_ryaoi_filler-0.4.4.dist-info/RECORD
